puber/__init__.py
puber/__version__.py
puber/cli.py
puber/norm/__init__.py
puber/norm/name.py
puber-0.1.1.dist-info/licenses/LICENSE
puber-0.1.1.dist-info/METADATA
puber-0.1.1.dist-info/WHEEL
puber-0.1.1.dist-info/entry_points.txt
puber-0.1.1.dist-info/top_level.txt
puber-0.1.1.dist-info/RECORD
