Metadata-Version: 2.4
Name: puber
Version: 0.1.1
Summary: Text tools for publishers.
Author-email: Timur Ulyahin <ucomru@pm.me>
License: MIT
Project-URL: Homepage, https://github.com/ucomru/python-puber
Project-URL: Repository, https://github.com/ucomru/python-puber
Project-URL: Documentation, https://github.com/ucomru/python-puber
Project-URL: Issues, https://github.com/ucomru/python-puber/issues
Keywords: text,normalization,publishing,documents,tools,cli
Classifier: Programming Language :: Python :: 3
Classifier: Operating System :: MacOS
Classifier: Operating System :: Microsoft :: Windows
Classifier: Operating System :: POSIX :: Linux
Classifier: Topic :: Text Processing
Classifier: Intended Audience :: Developers
Requires-Python: >=3.9
License-File: LICENSE
Requires-Dist: click
Dynamic: license-file
